netbox_wug_sync/__init__.py
netbox_wug_sync/admin.py
netbox_wug_sync/forms.py
netbox_wug_sync/jobs.py
netbox_wug_sync/models.py
netbox_wug_sync/navigation.py
netbox_wug_sync/signals.py
netbox_wug_sync/sync_utils.py
netbox_wug_sync/tables.py
netbox_wug_sync/urls.py
netbox_wug_sync/views.py
netbox_wug_sync/wug_client.py
netbox_wug_sync/api/__init__.py
netbox_wug_sync/api/serializers.py
netbox_wug_sync/api/urls.py
netbox_wug_sync/api/views.py
netbox_wug_sync/migrations/0001_initial.py
netbox_wug_sync/migrations/0002_fix_wugsynclog_fields.py
netbox_wug_sync/migrations/0003_fix_netboxipexport_schema.py
netbox_wug_sync/migrations/0004_add_netboxipexport_missing_fields.py
netbox_wug_sync/migrations/__init__.py
netbox_wug_sync/static/netbox_wug_sync/img/logo-instructions.txt
netbox_wug_sync/static/netbox_wug_sync/img/wug-logo.svg
netbox_wug_sync/templates/netbox_wug_sync/dashboard.html
netbox_wug_sync/templates/netbox_wug_sync/wugconnection_detail.html
netbox_wug_sync/templates/netbox_wug_sync/wugconnection_edit.html
netbox_wug_sync/templates/netbox_wug_sync/wugconnection_list.html
netbox_wug_sync/templates/netbox_wug_sync/wugdevice_list.html
netbox_wug_sync/templates/netbox_wug_sync/wugsynclog_list.html
netbox_wug_sync/templatetags/__init__.py
netbox_wug_sync/templatetags/wug_filters.py
netbox_wug_sync-0.1.0.dist-info/licenses/LICENSE
netbox_wug_sync-0.1.0.dist-info/METADATA
netbox_wug_sync-0.1.0.dist-info/WHEEL
netbox_wug_sync-0.1.0.dist-info/top_level.txt
netbox_wug_sync-0.1.0.dist-info/RECORD
