Metadata-Version: 2.4
Name: netbox-wug-sync
Version: 0.1.0
Summary: NetBox plugin for synchronizing devices with WhatsUp Gold
Author-email: Bryan <bryan@example.com>
License: Apache-2.0
Project-URL: Homepage, https://github.com/bassslap/netbox-wug-sync
Project-URL: Documentation, https://github.com/bassslap/netbox-wug-sync/wiki
Project-URL: Repository, https://github.com/bassslap/netbox-wug-sync
Project-URL: Bug Tracker, https://github.com/bassslap/netbox-wug-sync/issues
Keywords: netbox,plugin,whatsup-gold,network-monitoring,device-sync
Classifier: Development Status :: 3 - Alpha
Classifier: Intended Audience :: Developers
Classifier: Intended Audience :: System Administrators
Classifier: License :: OSI Approved :: Apache Software License
Classifier: Natural Language :: English
Classifier: Operating System :: OS Independent
Classifier: Programming Language :: Python :: 3 :: Only
Classifier: Programming Language :: Python :: 3.10
Classifier: Programming Language :: Python :: 3.11
Classifier: Programming Language :: Python :: 3.12
Classifier: Topic :: System :: Networking
Requires-Python: >=3.10
License-File: LICENSE
Requires-Dist: requests>=2.25.1
Requires-Dist: django>=4.2
Provides-Extra: dev
Requires-Dist: pytest>=7.0.0; extra == "dev"
Requires-Dist: pytest-django>=4.5.0; extra == "dev"
Requires-Dist: black>=22.0.0; extra == "dev"
Requires-Dist: isort>=5.10.0; extra == "dev"
Requires-Dist: flake8>=4.0.0; extra == "dev"
Dynamic: license-file
